model_ensembler/__init__.py
model_ensembler/batcher.py
model_ensembler/cli.py
model_ensembler/config.py
model_ensembler/exceptions.py
model_ensembler/model-ensemble.json
model_ensembler/runners.py
model_ensembler/templates.py
model_ensembler/utils.py
model_ensembler/cluster/__init__.py
model_ensembler/cluster/dummy.py
model_ensembler/cluster/slurm.py
model_ensembler/tasks/__init__.py
model_ensembler/tasks/exceptions.py
model_ensembler/tasks/hpc.py
model_ensembler/tasks/sys.py
model_ensembler/tasks/utils.py
model_ensembler-0.6.2.dist-info/licenses/LICENSE
model_ensembler-0.6.2.dist-info/METADATA
model_ensembler-0.6.2.dist-info/WHEEL
model_ensembler-0.6.2.dist-info/entry_points.txt
model_ensembler-0.6.2.dist-info/top_level.txt
model_ensembler-0.6.2.dist-info/RECORD
