Metadata-Version: 2.4
Name: model-ensembler
Version: 0.6.2
Summary: Model Ensembler for managed batch workflows
Author-email: James Byrne <jambyr@bas.ac.uk>
Maintainer-email: James Byrne <jambyr@bas.ac.uk>, Thomas Zwagerman <thozwa@bas.ac.uk>
License-Expression: MIT
Project-URL: Homepage, https://www.github.com/jimcircadian/model-ensembler
Project-URL: Bug Tracker, https://www.github.com/jimcircadian/model-ensembler/issues
Project-URL: Change Log, https://github.com/environmental-forecasting/model-ensembler/blob/main/CHANGELOG.md
Keywords: slurm,hpc,tools,batch,model,ensemble,local
Classifier: Environment :: Console
Classifier: Programming Language :: Python :: 3
Classifier: Programming Language :: Python :: 3.7
Classifier: Programming Language :: Python :: 3.8
Classifier: Programming Language :: Python :: 3.9
Classifier: Programming Language :: Python :: 3.10
Classifier: Programming Language :: Python :: 3.11
Classifier: Programming Language :: Python :: 3.12
Classifier: Intended Audience :: Science/Research
Classifier: Intended Audience :: System Administrators
Classifier: Operating System :: POSIX
Classifier: Development Status :: 3 - Alpha
Classifier: Topic :: System :: Distributed Computing
Requires-Python: >=3.7
License-File: LICENSE
Requires-Dist: jinja2
Requires-Dist: jsonschema
Requires-Dist: pyyaml
Provides-Extra: tests
Requires-Dist: pytest; extra == "tests"
Requires-Dist: pytest-cov; extra == "tests"
Provides-Extra: lint
Requires-Dist: flake8; extra == "lint"
Provides-Extra: docs
Requires-Dist: mkdocs; extra == "docs"
Requires-Dist: mkdocs-material; extra == "docs"
Requires-Dist: mkdocstrings[python]; extra == "docs"
Requires-Dist: mkdocs-autoapi; extra == "docs"
Requires-Dist: mkdocs-git-authors-plugin; extra == "docs"
Dynamic: license-file
